ztDemo
