Metadata-Version: 1.0
Name: ztDemo
Version: 0.0.26
Summary: a common test framework support for both UI and API test with run in parallel ability.
Home-page: https://www.testertalk.com
Author: kevin.cai
Author-email: 不告诉你@outlook.com
License: MIT
Platform: UNKNOWN
